reqcheq/__init__.py
reqcheq/reqcheq.py
reqcheq-0.0.4.dist-info/LICENSE
reqcheq-0.0.4.dist-info/METADATA
reqcheq-0.0.4.dist-info/WHEEL
reqcheq-0.0.4.dist-info/top_level.txt
reqcheq-0.0.4.dist-info/RECORD
