Metadata-Version: 2.1
Name: reqcheq
Version: 0.0.4
Summary: Automatically check and install modules
Home-page: https://github.com/nandobfer/reqcheq
Author: nandobfer
Author-email: nandobfer@yahoo.com.br
Project-URL: Bug Tracker, https://github.com/nandobfer/reqcheq/issues
Classifier: Programming Language :: Python :: 3
Classifier: License :: OSI Approved :: MIT License
Classifier: Operating System :: OS Independent
Requires-Python: >=3.6
License-File: LICENSE
